remove_dagmc_tags/__init__.py
remove_dagmc_tags/core.py
remove_dagmc_tags-0.0.5.data/scripts/remove-dagmc-tags
tests/__init__.py
tests/dagmc.h5m
tests/test_command_line_tool.py
tests/test_python_api.py
remove_dagmc_tags-0.0.5.dist-info/LICENSE
remove_dagmc_tags-0.0.5.dist-info/METADATA
remove_dagmc_tags-0.0.5.dist-info/WHEEL
remove_dagmc_tags-0.0.5.dist-info/top_level.txt
remove_dagmc_tags-0.0.5.dist-info/zip-safe
remove_dagmc_tags-0.0.5.dist-info/RECORD
