Metadata-Version: 2.1
Name: remove-dagmc-tags
Version: 0.0.5
Summary: A tool for selectively removing tags such as the graveyard from DAGMC h5m files.
Home-page: https://github.com/svalinn/remove_dagmc_tags
Author: DAGMC development team
License: UNKNOWN
Platform: UNKNOWN
Requires-Dist: numpy
